csseg/__init__.py
csseg/test.py
csseg/train.py
csseg/configs/__init__.py
csseg/configs/builder.py
csseg/configs/_base_/__init__.py
csseg/configs/_base_/dataloaders/__init__.py
csseg/configs/_base_/dataloaders/default_dataloader_bs24.py
csseg/configs/_base_/datasets/__init__.py
csseg/configs/_base_/datasets/vocaug_512x512.py
csseg/configs/_base_/optimizers/__init__.py
csseg/configs/_base_/optimizers/default_optimizer_sgd.py
csseg/configs/_base_/parallel/__init__.py
csseg/configs/_base_/parallel/default_parallel.py
csseg/configs/_base_/schedulers/__init__.py
csseg/configs/_base_/schedulers/default_scheduler_poly.py
csseg/modules/__init__.py
csseg/modules/datasets/__init__.py
csseg/modules/datasets/ade20k.py
csseg/modules/datasets/base.py
csseg/modules/datasets/builder.py
csseg/modules/datasets/voc.py
csseg/modules/datasets/pipelines/__init__.py
csseg/modules/datasets/pipelines/evaluators.py
csseg/modules/datasets/pipelines/transforms.py
csseg/modules/models/__init__.py
csseg/modules/models/decoders/__init__.py
csseg/modules/models/decoders/aspphead.py
csseg/modules/models/decoders/builder.py
csseg/modules/models/encoders/__init__.py
csseg/modules/models/encoders/builder.py
csseg/modules/models/encoders/resnet.py
csseg/modules/models/encoders/resnetmib.py
csseg/modules/models/encoders/resnetplop.py
csseg/modules/models/encoders/resnetrcil.py
csseg/modules/models/encoders/bricks/__init__.py
csseg/modules/models/encoders/bricks/activation/__init__.py
csseg/modules/models/encoders/bricks/activation/builder.py
csseg/modules/models/encoders/bricks/activation/convertor.py
csseg/modules/models/encoders/bricks/normalization/__init__.py
csseg/modules/models/encoders/bricks/normalization/builder.py
csseg/modules/models/losses/__init__.py
csseg/modules/models/losses/builder.py
csseg/modules/models/losses/celoss.py
csseg/modules/models/losses/csloss.py
csseg/modules/models/losses/klloss.py
csseg/modules/models/optimizers/__init__.py
csseg/modules/models/optimizers/builder.py
CSSegmentation-0.0.1.dist-info/LICENSE
CSSegmentation-0.0.1.dist-info/METADATA
CSSegmentation-0.0.1.dist-info/WHEEL
CSSegmentation-0.0.1.dist-info/top_level.txt
CSSegmentation-0.0.1.dist-info/zip-safe
CSSegmentation-0.0.1.dist-info/RECORD
