Metadata-Version: 2.1
Name: CSSegmentation
Version: 0.0.1
Summary: CSSegmentation: An Open Source Continual Semantic Segmentation Toolbox Based on PyTorch
Home-page: https://github.com/SegmentationBLWX/cssegmentation
Author: Zhenchao Jin
Author-email: charlesblwx@gmail.com
License: Apache License 2.0
Platform: UNKNOWN
Classifier: License :: OSI Approved :: Apache Software License
Classifier: Programming Language :: Python :: 3
Classifier: Intended Audience :: Developers
Classifier: Operating System :: OS Independent
License-File: LICENSE
Requires-Dist: pillow
Requires-Dist: pandas
Requires-Dist: opencv-python
Requires-Dist: numpy
Requires-Dist: scipy
Requires-Dist: cython
Requires-Dist: apex
Requires-Dist: tqdm
Requires-Dist: argparse
